opera/cli.py
opera/constants.py
opera/error.py
opera/storage.py
opera/utils.py
opera/value.py
opera/commands/__init__.py
opera/commands/deploy.py
opera/commands/diff.py
opera/commands/info.py
opera/commands/notify.py
opera/commands/outputs.py
opera/commands/package.py
opera/commands/undeploy.py
opera/commands/unpackage.py
opera/commands/update.py
opera/commands/validate.py
opera/compare/__init__.py
opera/compare/comparisons.py
opera/compare/diff.py
opera/compare/instance_comparer.py
opera/compare/template_comparer.py
opera/executors/__init__.py
opera/executors/ansible/__init__.py
opera/executors/ansible/ansible.py
opera/executors/ansible/utils.py
opera/executors/ansible/stdout_callbacks/__init__.py
opera/executors/ansible/stdout_callbacks/json_ansible_callback.py
opera/instance/__init__.py
opera/instance/base.py
opera/instance/node.py
opera/instance/relationship.py
opera/instance/topology.py
opera/threading/__init__.py
opera/threading/node_executor.py
opera/threading/utils.py
opera-0.7.0.dist-info/LICENSE
opera-0.7.0.dist-info/METADATA
opera-0.7.0.dist-info/WHEEL
opera-0.7.0.dist-info/entry_points.txt
opera-0.7.0.dist-info/top_level.txt
opera-0.7.0.dist-info/zip-safe
opera-0.7.0.dist-info/RECORD
