Metadata-Version: 2.1
Name: opera
Version: 0.7.0
Summary: Lightweight TOSCA orchestrator
Home-page: https://github.com/xlab-si/xopera-opera
Author: XLAB d.o.o.
Author-email: pypi@xlab.si
Maintainer: xOpera team
Maintainer-email: xopera@xlab.si
Project-URL: Documentation, https://xlab-si.github.io/xopera-docs/
Project-URL: Source Code, https://github.com/xlab-si/xopera-opera
Project-URL: Bug Tracker, https://github.com/xlab-si/xopera-opera/issues
Project-URL: Discussions, https://github.com/xlab-si/xopera-opera/discussions
Project-URL: Releases, https://github.com/xlab-si/xopera-opera/releases
Project-URL: Pre-releases, https://test.pypi.org/project/opera/#history
Project-URL: Examples, https://github.com/xlab-si/xopera-examples
Project-URL: CI, https://github.com/xlab-si/xopera-opera/actions
Project-URL: Coverage, https://codeclimate.com/github/xlab-si/xopera-opera
Keywords: orchestration
Classifier: Development Status :: 3 - Alpha
Classifier: Environment :: Console
Classifier: Intended Audience :: Developers
Classifier: Intended Audience :: System Administrators
Classifier: Intended Audience :: Science/Research
Classifier: Intended Audience :: Information Technology
Classifier: License :: OSI Approved :: Apache Software License
Classifier: Operating System :: POSIX
Classifier: Programming Language :: Python
Classifier: Programming Language :: Python :: 3
Classifier: Programming Language :: Python :: 3.8
Classifier: Programming Language :: Python :: 3.9
Classifier: Programming Language :: Python :: 3.10
Classifier: Programming Language :: Python :: 3.11
Classifier: Topic :: Software Development
Classifier: Topic :: Software Development :: Libraries
Classifier: Topic :: Software Development :: Libraries :: Python Modules
Classifier: Topic :: Utilities
Classifier: Framework :: Ansible
License-File: LICENSE
Requires-Dist: ansible-core (>=2.13.4)
Requires-Dist: pyyaml (<=5.4.1)
Requires-Dist: shtab (>=1.5.5)
Requires-Dist: opera-tosca-parser (>=0.2.2)
Provides-Extra: ansible
Requires-Dist: ansible (>=5.9.0) ; extra == 'ansible'
Provides-Extra: openstack
Requires-Dist: openstacksdk (>=0.99.0) ; extra == 'openstack'
Provides-Extra: tests
Requires-Dist: wheel (==0.37.1) ; extra == 'tests'
Requires-Dist: bandit (==1.7.4) ; extra == 'tests'
Requires-Dist: docutils (==0.18.1) ; extra == 'tests'
Requires-Dist: flake8 (==4.0.1) ; extra == 'tests'
Requires-Dist: flake8-import-order (==0.18.1) ; extra == 'tests'
Requires-Dist: mypy (==0.812) ; extra == 'tests'
Requires-Dist: pydocstyle (==6.1.1) ; extra == 'tests'
Requires-Dist: pylint (==2.13.4) ; extra == 'tests'
Requires-Dist: pytest (==7.1.3) ; extra == 'tests'
Requires-Dist: pytest-cov (==3.0.0) ; extra == 'tests'
Requires-Dist: selinux (==0.2.1) ; extra == 'tests'
